{
	"configurations" : 
	[
		{
			"directories" : 
			[
				{
					"build" : ".",
					"hasInstallRule" : true,
					"jsonFile" : "directory-.-d681ba079a8039763d1b.json",
					"minimumCMakeVersion" : 
					{
						"string" : "3.12"
					},
					"projectIndex" : 0,
					"source" : ".",
					"targetIndexes" : 
					[
						0,
						1
					]
				}
			],
			"name" : "",
			"projects" : 
			[
				{
					"directoryIndexes" : 
					[
						0
					],
					"name" : "omni_base_description",
					"targetIndexes" : 
					[
						0,
						1
					]
				}
			],
			"targets" : 
			[
				{
					"directoryIndex" : 0,
					"id" : "omni_base_description_uninstall::@6890427a1f51a3e7e1df",
					"jsonFile" : "target-omni_base_description_uninstall-390a62088cafdfd9c4d2.json",
					"name" : "omni_base_description_uninstall",
					"projectIndex" : 0
				},
				{
					"directoryIndex" : 0,
					"id" : "uninstall::@6890427a1f51a3e7e1df",
					"jsonFile" : "target-uninstall-672cd9307d49862b7c48.json",
					"name" : "uninstall",
					"projectIndex" : 0
				}
			]
		}
	],
	"kind" : "codemodel",
	"paths" : 
	{
		"build" : "/home/container_user/omni_ws/build/omni_base_description",
		"source" : "/home/container_user/omni_ws/src/omni_base_description"
	},
	"version" : 
	{
		"major" : 2,
		"minor" : 3
	}
}
